{
  "version": "2.3.0",
  "summary": {
    "title": "Initial Threat Model",
    "owner": "",
    "description": "",
    "id": 0
  },
  "detail": {
    "contributors": [],
    "diagrams": [
      {
        "id": 0,
        "title": "Initial Threat Model Diagram",
        "diagramType": "STRIDE",
        "placeholder": "New STRIDE diagram description",
        "thumbnail": "./public/content/images/thumbnail.stride.jpg",
        "version": "2.3.0",
        "cells": [
          {
            "position": {
              "x": 0,
              "y": 80
            },
            "size": {
              "width": 112.5,
              "height": 60
            },
            "attrs": {
              "text": {
                "text": "User"
              },
              "body": {
                "stroke": "#333333",
                "strokeWidth": 1.5,
                "strokeDasharray": null
              }
            },
            "visible": true,
            "shape": "actor",
            "ports": {
              "groups": {
                "top": {
                  "position": "top",
                  "attrs": {
                    "circle": {
                      "r": 4,
                      "magnet": true,
                      "stroke": "#5F95FF",
                      "strokeWidth": 1,
                      "fill": "#fff",
                      "style": {
                        "visibility": "hidden"
                      }
                    }
                  }
                },
                "right": {
                  "position": "right",
                  "attrs": {
                    "circle": {
                      "r": 4,
                      "magnet": true,
                      "stroke": "#5F95FF",
                      "strokeWidth": 1,
                      "fill": "#fff",
                      "style": {
                        "visibility": "hidden"
                      }
                    }
                  }
                },
                "bottom": {
                  "position": "bottom",
                  "attrs": {
                    "circle": {
                      "r": 4,
                      "magnet": true,
                      "stroke": "#5F95FF",
                      "strokeWidth": 1,
                      "fill": "#fff",
                      "style": {
                        "visibility": "hidden"
                      }
                    }
                  }
                },
                "left": {
                  "position": "left",
                  "attrs": {
                    "circle": {
                      "r": 4,
                      "magnet": true,
                      "stroke": "#5F95FF",
                      "strokeWidth": 1,
                      "fill": "#fff",
                      "style": {
                        "visibility": "hidden"
                      }
                    }
                  }
                }
              },
              "items": [
                {
                  "group": "top",
                  "id": "026045e9-d644-4b0d-8e97-ae70bca3d4a8"
                },
                {
                  "group": "right",
                  "id": "695b9213-513c-4adf-a26d-46f8f07b095e"
                },
                {
                  "group": "bottom",
                  "id": "433c1064-267c-45fb-8318-5416c85fba9e"
                },
                {
                  "group": "left",
                  "id": "af02bcaf-67fa-4995-8d7f-925d03e34090"
                }
              ]
            },
            "id": "f0ddb568-e8a5-44d5-b2b2-652fc5bd5a12",
            "zIndex": 1,
            "data": {
              "type": "tm.Actor",
              "name": "User",
              "description": "",
              "outOfScope": false,
              "reasonOutOfScope": "",
              "hasOpenThreats": false,
              "providesAuthentication": false,
              "threats": []
            }
          },
          {
            "position": {
              "x": 0,
              "y": 188
            },
            "size": {
              "width": 112.5,
              "height": 60
            },
            "attrs": {
              "text": {
                "text": "Admin"
              },
              "body": {
                "stroke": "#333333",
                "strokeWidth": 1.5,
                "strokeDasharray": null
              }
            },
            "visible": true,
            "shape": "actor",
            "ports": {
              "groups": {
                "top": {
                  "position": "top",
                  "attrs": {
                    "circle": {
                      "r": 4,
                      "magnet": true,
                      "stroke": "#5F95FF",
                      "strokeWidth": 1,
                      "fill": "#fff",
                      "style": {
                        "visibility": "hidden"
                      }
                    }
                  }
                },
                "right": {
                  "position": "right",
                  "attrs": {
                    "circle": {
                      "r": 4,
                      "magnet": true,
                      "stroke": "#5F95FF",
                      "strokeWidth": 1,
                      "fill": "#fff",
                      "style": {
                        "visibility": "hidden"
                      }
                    }
                  }
                },
                "bottom": {
                  "position": "bottom",
                  "attrs": {
                    "circle": {
                      "r": 4,
                      "magnet": true,
                      "stroke": "#5F95FF",
                      "strokeWidth": 1,
                      "fill": "#fff",
                      "style": {
                        "visibility": "hidden"
                      }
                    }
                  }
                },
                "left": {
                  "position": "left",
                  "attrs": {
                    "circle": {
                      "r": 4,
                      "magnet": true,
                      "stroke": "#5F95FF",
                      "strokeWidth": 1,
                      "fill": "#fff",
                      "style": {
                        "visibility": "hidden"
                      }
                    }
                  }
                }
              },
              "items": [
                {
                  "group": "top",
                  "id": "026045e9-d644-4b0d-8e97-ae70bca3d4a8"
                },
                {
                  "group": "right",
                  "id": "695b9213-513c-4adf-a26d-46f8f07b095e"
                },
                {
                  "group": "bottom",
                  "id": "433c1064-267c-45fb-8318-5416c85fba9e"
                },
                {
                  "group": "left",
                  "id": "af02bcaf-67fa-4995-8d7f-925d03e34090"
                }
              ]
            },
            "id": "0bd437dd-15d8-451c-aa73-247f05b273bf",
            "zIndex": 2,
            "data": {
              "type": "tm.Actor",
              "name": "Admin",
              "description": "",
              "outOfScope": false,
              "reasonOutOfScope": "",
              "hasOpenThreats": false,
              "providesAuthentication": false,
              "threats": []
            }
          },
          {
            "shape": "trust-boundary-curve",
            "width": 200,
            "height": 100,
            "zIndex": 10,
            "connector": "smooth",
            "data": {
              "type": "tm.Boundary",
              "name": "Trust Boundary",
              "description": "",
              "isTrustBoundary": true,
              "hasOpenThreats": false
            },
            "labels": [
              {
                "attrs": {
                  "label": {
                    "text": "Trust Boundary"
                  }
                }
              }
            ],
            "id": "63e1d8c2-5870-440d-90f7-1e378eaa213e",
            "source": {
              "x": 130,
              "y": 60
            },
            "target": {
              "x": 130,
              "y": 290
            }
          },
          {
            "shape": "flow",
            "attrs": {
              "line": {
                "stroke": "#333333",
                "targetMarker": {
                  "name": "block"
                },
                "sourceMarker": {
                  "name": ""
                },
                "strokeDasharray": null
              }
            },
            "width": 200,
            "height": 100,
            "zIndex": 10,
            "connector": "smooth",
            "data": {
              "type": "tm.Flow",
              "name": "Web\nServer",
              "description": "",
              "outOfScope": false,
              "reasonOutOfScope": "",
              "hasOpenThreats": false,
              "isBidirectional": false,
              "isEncrypted": false,
              "isPublicNetwork": false,
              "protocol": "",
              "threats": []
            },
            "labels": [
              "Web\nServer"
            ],
            "id": "a1252649-3d42-4202-ac57-c7d7169d1451",
            "source": {
              "cell": "1f4a689a-af10-4c82-848f-f6872c06581f"
            },
            "target": {
              "cell": "1f4a689a-af10-4c82-848f-f6872c06581f"
            },
            "parent": "1f4a689a-af10-4c82-848f-f6872c06581f"
          },
          {
            "shape": "flow",
            "attrs": {
              "line": {
                "stroke": "#333333",
                "targetMarker": {
                  "name": "block"
                },
                "sourceMarker": {
                  "name": ""
                },
                "strokeDasharray": null
              }
            },
            "width": 200,
            "height": 100,
            "zIndex": 10,
            "connector": "smooth",
            "data": {
              "type": "tm.Flow",
              "name": "Data Flow",
              "description": "",
              "outOfScope": false,
              "reasonOutOfScope": "",
              "hasOpenThreats": false,
              "isBidirectional": false,
              "isEncrypted": false,
              "isPublicNetwork": false,
              "protocol": "",
              "threats": []
            },
            "labels": [
              {
                "attrs": {
                  "label": {
                    "text": "Data Flow"
                  }
                }
              }
            ],
            "id": "dac41f3e-de60-4217-bd4c-0819ccdba26d",
            "source": {
              "x": 113,
              "y": 115
            },
            "target": {
              "cell": "1f4a689a-af10-4c82-848f-f6872c06581f",
              "port": "2b176090-e797-429a-aadc-5db4ad2a83df"
            }
          },
          {
            "shape": "flow",
            "attrs": {
              "line": {
                "stroke": "#333333",
                "targetMarker": {
                  "name": "block"
                },
                "sourceMarker": {
                  "name": ""
                },
                "strokeDasharray": null
              }
            },
            "width": 200,
            "height": 100,
            "zIndex": 10,
            "connector": "smooth",
            "data": {
              "type": "tm.Flow",
              "name": "Data Flow",
              "description": "",
              "outOfScope": false,
              "reasonOutOfScope": "",
              "hasOpenThreats": false,
              "isBidirectional": false,
              "isEncrypted": false,
              "isPublicNetwork": false,
              "protocol": "",
              "threats": []
            },
            "labels": [
              {
                "attrs": {
                  "label": {
                    "text": "Data Flow"
                  }
                }
              }
            ],
            "id": "cde643b8-24cc-4c89-a2ea-38c36f7f04e6",
            "source": {
              "x": 113,
              "y": 218
            },
            "target": {
              "cell": "1f4a689a-af10-4c82-848f-f6872c06581f",
              "port": "2b176090-e797-429a-aadc-5db4ad2a83df"
            }
          },
          {
            "shape": "flow",
            "attrs": {
              "line": {
                "stroke": "#333333",
                "targetMarker": {
                  "name": "block"
                },
                "sourceMarker": {
                  "name": ""
                },
                "strokeDasharray": null
              }
            },
            "width": 200,
            "height": 100,
            "zIndex": 10,
            "connector": "smooth",
            "data": {
              "type": "tm.Flow",
              "name": "",
              "description": "",
              "outOfScope": false,
              "reasonOutOfScope": "",
              "hasOpenThreats": false,
              "isBidirectional": false,
              "isEncrypted": false,
              "isPublicNetwork": false,
              "protocol": "",
              "threats": []
            },
            "labels": [
              ""
            ],
            "id": "e25dbfad-34db-459f-9a54-7e94cdebfef8",
            "source": {
              "x": 311,
              "y": 167
            },
            "target": {
              "cell": "500e2206-36c8-4eb0-aee5-407fb7fbc89a",
              "port": "2b176090-e797-429a-aadc-5db4ad2a83df"
            }
          },
          {
            "shape": "flow",
            "attrs": {
              "line": {
                "stroke": "#333333",
                "targetMarker": {
                  "name": "block"
                },
                "sourceMarker": {
                  "name": ""
                },
                "strokeDasharray": null
              }
            },
            "width": 200,
            "height": 100,
            "zIndex": 10,
            "connector": "smooth",
            "data": {
              "type": "tm.Flow",
              "name": "",
              "description": "",
              "outOfScope": false,
              "reasonOutOfScope": "",
              "hasOpenThreats": false,
              "isBidirectional": false,
              "isEncrypted": false,
              "isPublicNetwork": false,
              "protocol": "",
              "threats": []
            },
            "labels": [
              ""
            ],
            "id": "e059de07-ab6c-4ad9-afdf-ee72a20c0ed8",
            "source": {
              "x": 436,
              "y": 168
            },
            "target": {
              "cell": "0c0da23b-f4c8-44c6-b83d-063d6a478b00",
              "port": "e563955a-c3b4-458d-afac-9d6c9952c8ab"
            }
          },
          {
            "position": {
              "x": 251,
              "y": 140
            },
            "size": {
              "width": 60,
              "height": 60
            },
            "attrs": {
              "text": {
                "text": ""
              },
              "body": {
                "stroke": "red",
                "strokeWidth": 2.5,
                "strokeDasharray": null
              }
            },
            "visible": true,
            "shape": "process",
            "ports": {
              "groups": {
                "top": {
                  "position": "top",
                  "attrs": {
                    "circle": {
                      "r": 4,
                      "magnet": true,
                      "stroke": "#5F95FF",
                      "strokeWidth": 1,
                      "fill": "#fff",
                      "style": {
                        "visibility": "hidden"
                      }
                    }
                  }
                },
                "right": {
                  "position": "right",
                  "attrs": {
                    "circle": {
                      "r": 4,
                      "magnet": true,
                      "stroke": "#5F95FF",
                      "strokeWidth": 1,
                      "fill": "#fff",
                      "style": {
                        "visibility": "hidden"
                      }
                    }
                  }
                },
                "bottom": {
                  "position": "bottom",
                  "attrs": {
                    "circle": {
                      "r": 4,
                      "magnet": true,
                      "stroke": "#5F95FF",
                      "strokeWidth": 1,
                      "fill": "#fff",
                      "style": {
                        "visibility": "hidden"
                      }
                    }
                  }
                },
                "left": {
                  "position": "left",
                  "attrs": {
                    "circle": {
                      "r": 4,
                      "magnet": true,
                      "stroke": "#5F95FF",
                      "strokeWidth": 1,
                      "fill": "#fff",
                      "style": {
                        "visibility": "hidden"
                      }
                    }
                  }
                }
              },
              "items": [
                {
                  "group": "top",
                  "id": "3092c4b6-efc0-41b7-8863-93cb35be1d54"
                },
                {
                  "group": "right",
                  "id": "df78299f-de5d-484c-bcc2-be314e5d5d0e"
                },
                {
                  "group": "bottom",
                  "id": "c6bf4545-9b3a-4ec3-aed4-ed8e6f146482"
                },
                {
                  "group": "left",
                  "id": "2b176090-e797-429a-aadc-5db4ad2a83df"
                }
              ]
            },
            "id": "1f4a689a-af10-4c82-848f-f6872c06581f",
            "zIndex": 11,
            "data": {
              "type": "tm.Process",
              "name": "",
              "description": "",
              "outOfScope": false,
              "reasonOutOfScope": "",
              "hasOpenThreats": true,
              "handlesCardPayment": false,
              "handlesGoodsOrServices": false,
              "isWebApplication": false,
              "privilegeLevel": "",
              "threats": [
                {
                  "id": "b46ac9a7-1e69-42d8-8bb5-f2f5a6749c89",
                  "title": "New STRIDE threat",
                  "status": "Open",
                  "severity": "Medium",
                  "type": "Spoofing",
                  "description": "Manipulating authentication tokens to masquerade as a valid user. This threat undermines identity veri\u0000cation and can lead to unauthorized actions",
                  "mitigation": "Provide remediation for this threat or a reason if status is N/A",
                  "modelType": "STRIDE",
                  "new": false,
                  "number": 1,
                  "score": ""
                },
                {
                  "id": "1a22a746-0e6c-4264-8830-5e374eb31552",
                  "title": "New STRIDE threat",
                  "status": "Open",
                  "severity": "Medium",
                  "type": "Tampering",
                  "description": "Altering form data in transit (e.g. modifying an HTTP request) ",
                  "mitigation": "Provide remediation for this threat or a reason if status is N/A",
                  "modelType": "STRIDE",
                  "new": false,
                  "number": 2,
                  "score": ""
                },
                {
                  "id": "0997de74-0519-40d4-96f9-18ab99a83654",
                  "title": "New STRIDE threat",
                  "status": "Open",
                  "severity": "Medium",
                  "type": "Denial of service",
                  "description": "excessive requests, rendering unavailable to users. This can involve sending a flood of traffic to the server or exploiting resource-heavy application features.",
                  "mitigation": "Provide remediation for this threat or a reason if status is N/A",
                  "modelType": "STRIDE",
                  "new": false,
                  "number": 3,
                  "score": ""
                }
              ],
              "threatFrequency": {
                "spoofing": 1,
                "tampering": 1,
                "repudiation": 0,
                "informationDisclosure": 0,
                "denialOfService": 1,
                "elevationOfPrivilege": 0
              }
            },
            "children": [
              "a1252649-3d42-4202-ac57-c7d7169d1451"
            ],
            "tools": {
              "items": [
                "boundary",
                "button-remove"
              ],
              "name": null
            }
          },
          {
            "position": {
              "x": 376,
              "y": 140
            },
            "size": {
              "width": 60,
              "height": 60
            },
            "attrs": {
              "text": {
                "text": "App\nServer"
              },
              "body": {
                "stroke": "#333333",
                "strokeWidth": 1.5,
                "strokeDasharray": null
              }
            },
            "visible": true,
            "shape": "process",
            "ports": {
              "groups": {
                "top": {
                  "position": "top",
                  "attrs": {
                    "circle": {
                      "r": 4,
                      "magnet": true,
                      "stroke": "#5F95FF",
                      "strokeWidth": 1,
                      "fill": "#fff",
                      "style": {
                        "visibility": "hidden"
                      }
                    }
                  }
                },
                "right": {
                  "position": "right",
                  "attrs": {
                    "circle": {
                      "r": 4,
                      "magnet": true,
                      "stroke": "#5F95FF",
                      "strokeWidth": 1,
                      "fill": "#fff",
                      "style": {
                        "visibility": "hidden"
                      }
                    }
                  }
                },
                "bottom": {
                  "position": "bottom",
                  "attrs": {
                    "circle": {
                      "r": 4,
                      "magnet": true,
                      "stroke": "#5F95FF",
                      "strokeWidth": 1,
                      "fill": "#fff",
                      "style": {
                        "visibility": "hidden"
                      }
                    }
                  }
                },
                "left": {
                  "position": "left",
                  "attrs": {
                    "circle": {
                      "r": 4,
                      "magnet": true,
                      "stroke": "#5F95FF",
                      "strokeWidth": 1,
                      "fill": "#fff",
                      "style": {
                        "visibility": "hidden"
                      }
                    }
                  }
                }
              },
              "items": [
                {
                  "group": "top",
                  "id": "3092c4b6-efc0-41b7-8863-93cb35be1d54"
                },
                {
                  "group": "right",
                  "id": "df78299f-de5d-484c-bcc2-be314e5d5d0e"
                },
                {
                  "group": "bottom",
                  "id": "c6bf4545-9b3a-4ec3-aed4-ed8e6f146482"
                },
                {
                  "group": "left",
                  "id": "2b176090-e797-429a-aadc-5db4ad2a83df"
                }
              ]
            },
            "id": "500e2206-36c8-4eb0-aee5-407fb7fbc89a",
            "zIndex": 12,
            "data": {
              "type": "tm.Process",
              "name": "App\nServer",
              "description": "",
              "outOfScope": false,
              "reasonOutOfScope": "",
              "hasOpenThreats": false,
              "handlesCardPayment": false,
              "handlesGoodsOrServices": false,
              "isWebApplication": false,
              "privilegeLevel": "",
              "threats": []
            }
          },
          {
            "position": {
              "x": 512,
              "y": 140
            },
            "size": {
              "width": 120,
              "height": 60
            },
            "attrs": {
              "text": {
                "text": "Databse"
              },
              "topLine": {
                "strokeWidth": 1.5,
                "strokeDasharray": null
              },
              "bottomLine": {
                "strokeWidth": 1.5,
                "strokeDasharray": null
              }
            },
            "visible": true,
            "shape": "store",
            "ports": {
              "groups": {
                "top": {
                  "position": "top",
                  "attrs": {
                    "circle": {
                      "r": 4,
                      "magnet": true,
                      "stroke": "#5F95FF",
                      "strokeWidth": 1,
                      "fill": "#fff",
                      "style": {
                        "visibility": "hidden"
                      }
                    }
                  }
                },
                "right": {
                  "position": "right",
                  "attrs": {
                    "circle": {
                      "r": 4,
                      "magnet": true,
                      "stroke": "#5F95FF",
                      "strokeWidth": 1,
                      "fill": "#fff",
                      "style": {
                        "visibility": "hidden"
                      }
                    }
                  }
                },
                "bottom": {
                  "position": "bottom",
                  "attrs": {
                    "circle": {
                      "r": 4,
                      "magnet": true,
                      "stroke": "#5F95FF",
                      "strokeWidth": 1,
                      "fill": "#fff",
                      "style": {
                        "visibility": "hidden"
                      }
                    }
                  }
                },
                "left": {
                  "position": "left",
                  "attrs": {
                    "circle": {
                      "r": 4,
                      "magnet": true,
                      "stroke": "#5F95FF",
                      "strokeWidth": 1,
                      "fill": "#fff",
                      "style": {
                        "visibility": "hidden"
                      }
                    }
                  }
                }
              },
              "items": [
                {
                  "group": "top",
                  "id": "a07dd77e-7c6b-4f52-b785-b4cef32d5d10"
                },
                {
                  "group": "right",
                  "id": "3a9e2f8f-dc03-4a48-877a-9b3d0351ee71"
                },
                {
                  "group": "bottom",
                  "id": "4c6bf4b8-aa5b-4781-ae25-b1e087e036ca"
                },
                {
                  "group": "left",
                  "id": "e563955a-c3b4-458d-afac-9d6c9952c8ab"
                }
              ]
            },
            "id": "0c0da23b-f4c8-44c6-b83d-063d6a478b00",
            "zIndex": 13,
            "data": {
              "type": "tm.Store",
              "name": "Databse",
              "description": "",
              "outOfScope": false,
              "reasonOutOfScope": "",
              "hasOpenThreats": false,
              "isALog": false,
              "isEncrypted": false,
              "isSigned": false,
              "storesCredentials": false,
              "storesInventory": false,
              "threats": []
            }
          }
        ]
      }
    ],
    "diagramTop": 1,
    "reviewer": "",
    "threatTop": 3
  }
}